finetuna-0.1.6.dist-info/METADATA
finetuna-0.1.6.dist-info/WHEEL
finetuna-0.1.6.dist-info/entry_points.txt
finetuna/__init__.py
finetuna/device.py
finetuna/model.py
main/__init__.py
main/main.py
finetuna-0.1.6.dist-info/RECORD
