Metadata-Version: 2.1
Name: finetuna
Version: 0.1.6
Requires-Python: >=3.10
Requires-Dist: accelerate
Requires-Dist: bitsandbytes==0.42.0
Requires-Dist: diffusers
Requires-Dist: einops
Requires-Dist: evaluate
Requires-Dist: huggingface
Requires-Dist: pandas
Requires-Dist: peft
Requires-Dist: pyyaml
Requires-Dist: scikit-learn
Requires-Dist: torch
Requires-Dist: tqdm
Requires-Dist: transformers
Requires-Dist: trl
Requires-Dist: wandb
